<?xml version="1.0" encoding="utf-8"?>
<!DOCTYPE hibernate-mapping PUBLIC "-//Hibernate/Hibernate Mapping DTD 3.0//EN"
"http://hibernate.sourceforge.net/hibernate-mapping-3.0.dtd">
<!-- 
    Mapping file autogenerated by MyEclipse Persistence Tools
-->
<hibernate-mapping>
    <class name="com.crm.op.po.TRegister" table="T_REGISTER" schema="CRM">
        <comment>挂号</comment>
        <id name="id" type="java.lang.Long">
            <column name="ID" precision="22" scale="0" />
            <generator class="sequence" />
        </id>
        <property name="custName" type="java.lang.String">
            <column name="CUST_NAME" length="20">
                <comment>客户名称</comment>
            </column>
        </property>
        <property name="doctor" type="java.lang.String">
            <column name="DOCTOR" length="20">
                <comment>医生</comment>
            </column>
        </property>
        <property name="createDate" type="java.util.Date">
            <column name="CREATE_DATE" length="7">
                <comment>创建时间</comment>
            </column>
        </property>
        <property name="staff" type="java.lang.Long">
            <column name="STAFF" precision="22" scale="0">
                <comment>登记员工</comment>
            </column>
        </property>
        <property name="old" type="java.lang.Long">
            <column name="OLD" precision="22" scale="0">
                <comment>年龄</comment>
            </column>
        </property>
        <property name="garden" type="java.lang.String">
            <column name="GARDEN" length="10">
                <comment>性别</comment>
            </column>
        </property>
    </class>
</hibernate-mapping>
